pca9536/__init__.py
pca9536/_version.py
pca9536/pca9536.py
pca9536/py.typed
pca9536_driver-0.1.3.dist-info/LICENSE
pca9536_driver-0.1.3.dist-info/METADATA
pca9536_driver-0.1.3.dist-info/WHEEL
pca9536_driver-0.1.3.dist-info/top_level.txt
pca9536_driver-0.1.3.dist-info/RECORD
