Metadata-Version: 2.2
Name: pca9536-driver
Version: 0.1.3
Summary: Python driver for the PCA9536 GPIO expander.
Author-email: Rogier van der Geer <rogier@vander-geer.nl>
License: Apache License 2.0
Project-URL: Repository, https://github.com/rogiervandergeer/pca9536-driver
Classifier: Programming Language :: Python :: 3
Classifier: License :: OSI Approved :: Apache Software License
Classifier: Topic :: System :: Hardware :: Hardware Drivers
Classifier: Typing :: Typed
Requires-Python: >=3.9
License-File: LICENSE
Requires-Dist: smbus2>=0.3.0
